numcy/__init__.py
numcy/fastarray.c
numcy/fastarray.cpython-311-darwin.so
numcy/fastarray.pxd
numcy/fastarray.pyx
numcy/utils.pyx
numcy-0.1.0.dist-info/licenses/LICENSE
numcy-0.1.0.dist-info/METADATA
numcy-0.1.0.dist-info/WHEEL
numcy-0.1.0.dist-info/top_level.txt
numcy-0.1.0.dist-info/RECORD
