Metadata-Version: 2.4
Name: numcy
Version: 0.1.0
Summary: Fast Cython-based NumPy-like arrays for high-performance computing
Author-email: Your Name <you@example.com>
License: MIT
Keywords: cython,numpy,linear algebra,high-performance
Classifier: Programming Language :: Python :: 3
Classifier: Programming Language :: Cython
Classifier: License :: OSI Approved :: MIT License
Classifier: Operating System :: OS Independent
Classifier: Intended Audience :: Science/Research
Requires-Python: >=3.8
License-File: LICENSE
Dynamic: license-file
Dynamic: requires-python
